snldata/__init__.py
snldata/client.py
snldata-1.1.4.dist-info/licenses/LICENSE
snldata-1.1.4.dist-info/METADATA
snldata-1.1.4.dist-info/WHEEL
snldata-1.1.4.dist-info/top_level.txt
snldata-1.1.4.dist-info/RECORD
